puissant/__init__.py
puissant-0.1.0.dist-info/LICENSE
puissant-0.1.0.dist-info/METADATA
puissant-0.1.0.dist-info/WHEEL
puissant-0.1.0.dist-info/top_level.txt
puissant-0.1.0.dist-info/RECORD
