Metadata-Version: 2.1
Name: puissant
Version: 0.1.0
Summary: validated python command line user input
Author: Alberto Garcia Izquierdo
Project-URL: repository, https://github.com/alb-garcia/puissant
Project-URL: home, https://github.com/alb-garcia/puissant
Project-URL: documentation, https://puissant.readthedocs.io
Classifier: Programming Language :: Python :: 3
Classifier: License :: OSI Approved :: MIT License
Requires-Python: >=3.7
License-File: LICENSE
